MANIFEST.in
README.md
setup.py
Xshm/Xshm.c
ueberzug/__init__.py
ueberzug/__main__.py
ueberzug/action.py
ueberzug/batch.py
ueberzug/conversion.py
ueberzug/files.py
ueberzug/geometry.py
ueberzug/layer.py
ueberzug/library.py
ueberzug/loading.py
ueberzug/parser.py
ueberzug/pattern.py
ueberzug/process.py
ueberzug/query_windows.py
ueberzug/scaling.py
ueberzug/terminal.py
ueberzug/thread.py
ueberzug/tmux_util.py
ueberzug/ui.py
ueberzug/version.py
ueberzug/xutil.py
ueberzug.egg-info/PKG-INFO
ueberzug.egg-info/SOURCES.txt
ueberzug.egg-info/dependency_links.txt
ueberzug.egg-info/entry_points.txt
ueberzug.egg-info/requires.txt
ueberzug.egg-info/top_level.txt
ueberzug/lib/__init__.py
ueberzug/lib/lib.sh
ueberzug/lib/v0/__init__.py