Metadata-Version: 1.2
Name: ueberzug
Version: 18.1.9
Summary: ueberzug is a command line util which allows to display images in combination with X11
Home-page: https://github.com/seebye/ueberzug
Author: Nico Baeurer
License: GPLv3
Project-URL: Bug Reports, https://github.com/seebye/ueberzug/issues
Project-URL: Source, https://github.com/seebye/ueberzug
Keywords: image media terminal ui gui
Platform: UNKNOWN
Classifier: Environment :: Console
Classifier: Environment :: X11 Applications
Classifier: Intended Audience :: Developers
Classifier: Operating System :: POSIX :: Linux
Classifier: Topic :: Software Development :: User Interfaces
Classifier: Topic :: Utilities
Requires-Python: >=3.6
